vgem/__init__.py
vgem/em.py
vgem/utils/__init__.py
vgem/utils/base64ec.py
vgem/utils/decrypt.py
vgem/utils/deserialize.py
vgem/utils/encrypt.py
vgem/utils/generate.py
vgem/utils/hash.py
vgem/utils/serialize.py
vgem/utils/fernet/__init__.py
vgem/utils/fernet/decrypt_fernet.py
vgem/utils/fernet/deserialize_fernet.py
vgem/utils/fernet/encrypt_fernet.py
vgem/utils/fernet/generate_fernet.py
vgem/utils/fernet/load_fernet.py
vgem/utils/fernet/serialize_fernet.py
vgem-1.3.0.dist-info/LICENSE
vgem-1.3.0.dist-info/METADATA
vgem-1.3.0.dist-info/WHEEL
vgem-1.3.0.dist-info/top_level.txt
vgem-1.3.0.dist-info/RECORD
