Metadata-Version: 2.1
Name: vgem
Version: 1.3.0
Summary: VerseGroups encryption manager class (RSA and Fernet wrapped AES sessions through RSA) for secure transmission of data. Also includes utilities such as hashing, salting and base64 encoding.
Home-page: https://github.com/VerseGroup/vgem-python
Author: VERSEGROUPLLC
Author-email: officialversegroupllc@gmail.com
License: MIT
Keywords: RSA,FERNET,hash,vgem,Encryption Manager,Encryption,Verse Group
Platform: UNKNOWN
Classifier: License :: OSI Approved :: MIT License
Classifier: Programming Language :: Python :: 3
Classifier: Programming Language :: Python :: 3.7
Classifier: Programming Language :: Python :: 3.9
Classifier: Programming Language :: Python :: 3.10
Classifier: Natural Language :: English
Classifier: Operating System :: MacOS :: MacOS X
Classifier: Operating System :: POSIX
Classifier: Operating System :: POSIX :: BSD
Classifier: Operating System :: POSIX :: Linux
Classifier: Operating System :: Microsoft :: Windows
Requires-Python: >=3.6
License-File: LICENSE
Requires-Dist: cryptography
Requires-Dist: pycparser
Requires-Dist: cffi
